bicleaner_ai_glove.libs/libgomp-a34b3233.so.1.0.0
bicleaner_ai_glove-0.2.1.dist-info/METADATA
bicleaner_ai_glove-0.2.1.dist-info/top_level.txt
bicleaner_ai_glove-0.2.1.dist-info/LICENSE
bicleaner_ai_glove-0.2.1.dist-info/WHEEL
bicleaner_ai_glove-0.2.1.dist-info/RECORD
glove/corpus_cython.cpython-310-x86_64-linux-gnu.so
glove/corpus.py
glove/__init__.py
glove/glove_cython.cpython-310-x86_64-linux-gnu.so
glove/glove.py
glove/metrics/accuracy.py
glove/metrics/__init__.py
glove/metrics/accuracy_cython.cpython-310-x86_64-linux-gnu.so
